textbasic/__init__.py
textbasic/utils.py
textbasic/basic/__init__.py
textbasic/basic/dictionary.json
textbasic/basic/preprocessor.py
textbasic/compare/__init__.py
textbasic/compare/similarityanalysis.py
textbasic-0.1.7.dist-info/METADATA
textbasic-0.1.7.dist-info/WHEEL
textbasic-0.1.7.dist-info/top_level.txt
textbasic-0.1.7.dist-info/RECORD
