Metadata-Version: 2.4
Name: textbasic
Version: 0.1.7
Summary: Text preprocessing package
Author-email: kimyh <kim_yh663927@naver.com>
License: MIT
Classifier: Programming Language :: Python :: 3
Classifier: License :: OSI Approved :: MIT License
Classifier: Operating System :: OS Independent
Requires-Python: >=3.7
Requires-Dist: pandas>=2.2.0
Requires-Dist: konlpy>=0.6.0
Requires-Dist: emoji>=2.14.1
Requires-Dist: pyarrow>=19.0.1
